{
    "resourceType": "Condition",
    "id": "21985",
    "meta": {
        "versionId": "2",
        "lastUpdated": "2022-12-22T11:48:27.534+01:00",
        "source": "#TlkwAeMFpSiYjyUW"
    },
    "extension": [
        {
            "url": "http://hl7.org/fhir/StructureDefinition/condition-related",
            "valueReference": {
                "reference": "Condition/20953"
            }
        }
    ],
    "code": {
        "coding": [
            {
                "system": "http://snomed.info/sct",
                "code": "10295004"
            }
        ]
    },
    "subject": {
        "reference": "Patient/20952"
    }
}
